{
  "image_path": "C:\\Projects\\PoseEstimation\\pose_images_backup\\c3da00c_added_photos\\img_33.jpg",
  "image_name": "img_33.jpg",
  "detections": [
    {
      "bbox_xyxy": [
        312.3338623046875,
        78.43698120117188,
        523.314453125,
        446.3013000488281
      ],
      "box_confidence": 0.9090785980224609,
      "class_id": 0,
      "class_name": "person",
      "keypoints": {
        "nose": {
          "x": 415.7245178222656,
          "y": 121.02899169921875,
          "confidence": 0.992254376411438
        },
        "left_eye": {
          "x": 425.3136291503906,
          "y": 114.43962097167969,
          "confidence": 0.9711712002754211
        },
        "right_eye": {
          "x": 408.1608581542969,
          "y": 115.00621032714844,
          "confidence": 0.9734997153282166
        },
        "left_ear": {
          "x": 439.44598388671875,
          "y": 120.12823486328125,
          "confidence": 0.8252773284912109
        },
        "right_ear": {
          "x": 397.9433288574219,
          "y": 121.41818237304688,
          "confidence": 0.7881409525871277
        },
        "left_shoulder": {
          "x": 457.7462158203125,
          "y": 155.9757080078125,
          "confidence": 0.9958776235580444
        },
        "right_shoulder": {
          "x": 387.2883605957031,
          "y": 167.4228973388672,
          "confidence": 0.9972209930419922
        },
        "left_elbow": {
          "x": 503.0068359375,
          "y": 185.52301025390625,
          "confidence": 0.9790405035018921
        },
        "right_elbow": {
          "x": 360.34375,
          "y": 219.08917236328125,
          "confidence": 0.9883546829223633
        },
        "left_wrist": {
          "x": 505.00457763671875,
          "y": 205.38409423828125,
          "confidence": 0.9756835103034973
        },
        "right_wrist": {
          "x": 357.22149658203125,
          "y": 252.824951171875,
          "confidence": 0.9833242893218994
        },
        "left_hip": {
          "x": 439.4927062988281,
          "y": 258.1512451171875,
          "confidence": 0.9968241453170776
        },
        "right_hip": {
          "x": 397.33270263671875,
          "y": 262.173828125,
          "confidence": 0.9974844455718994
        },
        "left_knee": {
          "x": 414.47222900390625,
          "y": 272.42181396484375,
          "confidence": 0.9927917718887329
        },
        "right_knee": {
          "x": 378.233154296875,
          "y": 291.3499450683594,
          "confidence": 0.9947524070739746
        },
        "left_ankle": {
          "x": 381.072265625,
          "y": 360.35845947265625,
          "confidence": 0.9573730826377869
        },
        "right_ankle": {
          "x": 374.5828857421875,
          "y": 392.40313720703125,
          "confidence": 0.963953971862793
        }
      }
    }
  ]
}