{
  "image_path": "C:\\Projects\\PoseEstimation\\pose_images_backup\\c3da00c_added_photos\\img_101.jpg",
  "image_name": "img_101.jpg",
  "detections": [
    {
      "bbox_xyxy": [
        138.6023406982422,
        0.42755126953125,
        396.82073974609375,
        465.8514404296875
      ],
      "box_confidence": 0.7966431975364685,
      "class_id": 0,
      "class_name": "person",
      "keypoints": {
        "nose": {
          "x": 384.37127685546875,
          "y": 18.480194091796875,
          "confidence": 0.5000813007354736
        },
        "left_eye": {
          "x": 384.1286315917969,
          "y": 6.98431396484375,
          "confidence": 0.028514139354228973
        },
        "right_eye": {
          "x": 383.32763671875,
          "y": 11.428131103515625,
          "confidence": 0.7217641472816467
        },
        "left_ear": {
          "x": 351.8319396972656,
          "y": 0.0,
          "confidence": 0.03844151645898819
        },
        "right_ear": {
          "x": 366.624755859375,
          "y": 13.680084228515625,
          "confidence": 0.9692089557647705
        },
        "left_shoulder": {
          "x": 297.792236328125,
          "y": 33.722747802734375,
          "confidence": 0.8678723573684692
        },
        "right_shoulder": {
          "x": 329.267578125,
          "y": 53.62724304199219,
          "confidence": 0.9926497340202332
        },
        "left_elbow": {
          "x": 284.57330322265625,
          "y": 102.91310119628906,
          "confidence": 0.5617685914039612
        },
        "right_elbow": {
          "x": 307.7011413574219,
          "y": 143.15809631347656,
          "confidence": 0.984968900680542
        },
        "left_wrist": {
          "x": 307.5105285644531,
          "y": 174.05032348632812,
          "confidence": 0.620914101600647
        },
        "right_wrist": {
          "x": 323.15899658203125,
          "y": 234.11648559570312,
          "confidence": 0.9509397149085999
        },
        "left_hip": {
          "x": 183.2955322265625,
          "y": 146.94012451171875,
          "confidence": 0.9943180680274963
        },
        "right_hip": {
          "x": 202.0565643310547,
          "y": 153.9188232421875,
          "confidence": 0.9982621073722839
        },
        "left_knee": {
          "x": 210.36920166015625,
          "y": 259.4359436035156,
          "confidence": 0.9957221746444702
        },
        "right_knee": {
          "x": 236.08401489257812,
          "y": 282.65460205078125,
          "confidence": 0.9986473917961121
        },
        "left_ankle": {
          "x": 214.47970581054688,
          "y": 382.4381103515625,
          "confidence": 0.976760983467102
        },
        "right_ankle": {
          "x": 205.12847900390625,
          "y": 416.360107421875,
          "confidence": 0.9862557053565979
        }
      }
    },
    {
      "bbox_xyxy": [
        308.18768310546875,
        207.4771270751953,
        423.35565185546875,
        384.40789794921875
      ],
      "box_confidence": 0.6132463216781616,
      "class_id": 0,
      "class_name": "person",
      "keypoints": {
        "nose": {
          "x": 395.3450622558594,
          "y": 277.70361328125,
          "confidence": 0.6636340618133545
        },
        "left_eye": {
          "x": 399.7589111328125,
          "y": 273.202880859375,
          "confidence": 0.28155460953712463
        },
        "right_eye": {
          "x": 395.8820495605469,
          "y": 273.0101013183594,
          "confidence": 0.7349905371665955
        },
        "left_ear": {
          "x": 397.0001525878906,
          "y": 258.8744201660156,
          "confidence": 0.13947169482707977
        },
        "right_ear": {
          "x": 385.9918212890625,
          "y": 258.942626953125,
          "confidence": 0.7222436666488647
        },
        "left_shoulder": {
          "x": 365.53460693359375,
          "y": 248.98281860351562,
          "confidence": 0.7236917614936829
        },
        "right_shoulder": {
          "x": 363.8955078125,
          "y": 255.64195251464844,
          "confidence": 0.9500302076339722
        },
        "left_elbow": {
          "x": 343.8416748046875,
          "y": 285.3658447265625,
          "confidence": 0.46224892139434814
        },
        "right_elbow": {
          "x": 343.64520263671875,
          "y": 305.72198486328125,
          "confidence": 0.9049271941184998
        },
        "left_wrist": {
          "x": 340.75970458984375,
          "y": 334.1382751464844,
          "confidence": 0.5014141201972961
        },
        "right_wrist": {
          "x": 347.874755859375,
          "y": 356.89935302734375,
          "confidence": 0.8289604187011719
        },
        "left_hip": {
          "x": 313.7406005859375,
          "y": 246.68161010742188,
          "confidence": 0.8948493599891663
        },
        "right_hip": {
          "x": 312.11859130859375,
          "y": 250.18153381347656,
          "confidence": 0.9478337168693542
        },
        "left_knee": {
          "x": 327.1965637207031,
          "y": 289.15936279296875,
          "confidence": 0.9311623573303223
        },
        "right_knee": {
          "x": 336.1288146972656,
          "y": 298.59332275390625,
          "confidence": 0.9664970636367798
        },
        "left_ankle": {
          "x": 326.1994323730469,
          "y": 348.5804748535156,
          "confidence": 0.9029228091239929
        },
        "right_ankle": {
          "x": 346.1220703125,
          "y": 364.6358642578125,
          "confidence": 0.936962902545929
        }
      }
    }
  ]
}