{
  "image_path": "C:\\Projects\\PoseEstimation\\pose_images_backup\\c3da00c_added_photos\\img_183.jpg",
  "image_name": "img_183.jpg",
  "detections": [
    {
      "bbox_xyxy": [
        15.615398406982422,
        19.3828125,
        114.08848571777344,
        425.31982421875
      ],
      "box_confidence": 0.8534829020500183,
      "class_id": 0,
      "class_name": "person",
      "keypoints": {
        "nose": {
          "x": 102.00408935546875,
          "y": 68.83099365234375,
          "confidence": 0.7904627323150635
        },
        "left_eye": {
          "x": 102.6662826538086,
          "y": 63.27166748046875,
          "confidence": 0.15531842410564423
        },
        "right_eye": {
          "x": 100.66249084472656,
          "y": 61.144775390625,
          "confidence": 0.8859859704971313
        },
        "left_ear": {
          "x": 83.6717300415039,
          "y": 61.846099853515625,
          "confidence": 0.049014847725629807
        },
        "right_ear": {
          "x": 80.98352813720703,
          "y": 57.90899658203125,
          "confidence": 0.9493942260742188
        },
        "left_shoulder": {
          "x": 70.42365264892578,
          "y": 100.03268432617188,
          "confidence": 0.8555646538734436
        },
        "right_shoulder": {
          "x": 57.19978332519531,
          "y": 100.17903900146484,
          "confidence": 0.9925705790519714
        },
        "left_elbow": {
          "x": 73.46389770507812,
          "y": 167.47735595703125,
          "confidence": 0.43778666853904724
        },
        "right_elbow": {
          "x": 59.29084396362305,
          "y": 168.41458129882812,
          "confidence": 0.98209148645401
        },
        "left_wrist": {
          "x": 89.27011108398438,
          "y": 219.74456787109375,
          "confidence": 0.4602029025554657
        },
        "right_wrist": {
          "x": 85.30610656738281,
          "y": 225.39276123046875,
          "confidence": 0.9512530565261841
        },
        "left_hip": {
          "x": 62.85176467895508,
          "y": 221.464111328125,
          "confidence": 0.9865086674690247
        },
        "right_hip": {
          "x": 55.08549499511719,
          "y": 222.60069274902344,
          "confidence": 0.9969467520713806
        },
        "left_knee": {
          "x": 60.11197280883789,
          "y": 305.0378723144531,
          "confidence": 0.9852989912033081
        },
        "right_knee": {
          "x": 59.11070251464844,
          "y": 310.3912353515625,
          "confidence": 0.9965580105781555
        },
        "left_ankle": {
          "x": 51.741050720214844,
          "y": 385.03033447265625,
          "confidence": 0.9574094414710999
        },
        "right_ankle": {
          "x": 53.93341827392578,
          "y": 397.1523132324219,
          "confidence": 0.981762170791626
        }
      }
    },
    {
      "bbox_xyxy": [
        281.4495849609375,
        274.7189636230469,
        423.5574951171875,
        361.6031188964844
      ],
      "box_confidence": 0.8238772749900818,
      "class_id": 0,
      "class_name": "person",
      "keypoints": {
        "nose": {
          "x": 386.114990234375,
          "y": 344.45123291015625,
          "confidence": 0.6067363619804382
        },
        "left_eye": {
          "x": 387.3977966308594,
          "y": 343.4907531738281,
          "confidence": 0.4337539076805115
        },
        "right_eye": {
          "x": 385.8143615722656,
          "y": 342.23876953125,
          "confidence": 0.43879982829093933
        },
        "left_ear": {
          "x": 391.89520263671875,
          "y": 337.45391845703125,
          "confidence": 0.3069576621055603
        },
        "right_ear": {
          "x": 379.5657043457031,
          "y": 333.951904296875,
          "confidence": 0.3362971842288971
        },
        "left_shoulder": {
          "x": 397.7599792480469,
          "y": 327.4449768066406,
          "confidence": 0.9281371831893921
        },
        "right_shoulder": {
          "x": 357.6082763671875,
          "y": 313.7943420410156,
          "confidence": 0.9261941313743591
        },
        "left_elbow": {
          "x": 413.1143798828125,
          "y": 335.1125793457031,
          "confidence": 0.9118947386741638
        },
        "right_elbow": {
          "x": 314.4890441894531,
          "y": 312.1377258300781,
          "confidence": 0.9090893268585205
        },
        "left_wrist": {
          "x": 417.87481689453125,
          "y": 346.371337890625,
          "confidence": 0.8960933685302734
        },
        "right_wrist": {
          "x": 314.7227783203125,
          "y": 341.5343933105469,
          "confidence": 0.8894510865211487
        },
        "left_hip": {
          "x": 358.3526306152344,
          "y": 286.9444274902344,
          "confidence": 0.9688203930854797
        },
        "right_hip": {
          "x": 335.0565490722656,
          "y": 278.9468994140625,
          "confidence": 0.9662834405899048
        },
        "left_knee": {
          "x": 338.2041320800781,
          "y": 319.832275390625,
          "confidence": 0.9168109893798828
        },
        "right_knee": {
          "x": 318.3296813964844,
          "y": 313.28741455078125,
          "confidence": 0.9163112640380859
        },
        "left_ankle": {
          "x": 316.37091064453125,
          "y": 318.8978576660156,
          "confidence": 0.7782201170921326
        },
        "right_ankle": {
          "x": 300.87359619140625,
          "y": 312.3209228515625,
          "confidence": 0.7805724740028381
        }
      }
    }
  ]
}