{
  "image_path": "C:\\Projects\\PoseEstimation\\pose_images_backup\\c3da00c_added_photos\\img_49.jpg",
  "image_name": "img_49.jpg",
  "detections": [
    {
      "bbox_xyxy": [
        432.6739501953125,
        53.067901611328125,
        570.7438354492188,
        409.1299743652344
      ],
      "box_confidence": 0.9180237054824829,
      "class_id": 0,
      "class_name": "person",
      "keypoints": {
        "nose": {
          "x": 491.05181884765625,
          "y": 111.43439483642578,
          "confidence": 0.9756163358688354
        },
        "left_eye": {
          "x": 494.83160400390625,
          "y": 102.96733856201172,
          "confidence": 0.9450076222419739
        },
        "right_eye": {
          "x": 483.8634338378906,
          "y": 106.93219757080078,
          "confidence": 0.8671085834503174
        },
        "left_ear": {
          "x": 511.0843505859375,
          "y": 86.85952758789062,
          "confidence": 0.8596287369728088
        },
        "right_ear": {
          "x": 483.3491516113281,
          "y": 98.55142211914062,
          "confidence": 0.474982351064682
        },
        "left_shoulder": {
          "x": 544.2567749023438,
          "y": 111.50559997558594,
          "confidence": 0.9972146153450012
        },
        "right_shoulder": {
          "x": 482.3141784667969,
          "y": 121.28748321533203,
          "confidence": 0.9946958422660828
        },
        "left_elbow": {
          "x": 559.8812866210938,
          "y": 172.02877807617188,
          "confidence": 0.9907612204551697
        },
        "right_elbow": {
          "x": 474.435791015625,
          "y": 177.29086303710938,
          "confidence": 0.980963945388794
        },
        "left_wrist": {
          "x": 541.2533569335938,
          "y": 224.45314025878906,
          "confidence": 0.9836668968200684
        },
        "right_wrist": {
          "x": 456.9483947753906,
          "y": 220.75314331054688,
          "confidence": 0.9701093435287476
        },
        "left_hip": {
          "x": 526.065673828125,
          "y": 231.29885864257812,
          "confidence": 0.9993696808815002
        },
        "right_hip": {
          "x": 487.344482421875,
          "y": 231.18853759765625,
          "confidence": 0.9991827607154846
        },
        "left_knee": {
          "x": 521.8260498046875,
          "y": 306.1741638183594,
          "confidence": 0.9979367256164551
        },
        "right_knee": {
          "x": 483.9751892089844,
          "y": 301.7797546386719,
          "confidence": 0.9976396560668945
        },
        "left_ankle": {
          "x": 514.1918334960938,
          "y": 370.3031005859375,
          "confidence": 0.9851137399673462
        },
        "right_ankle": {
          "x": 478.2375183105469,
          "y": 363.07647705078125,
          "confidence": 0.9847913384437561
        }
      }
    },
    {
      "bbox_xyxy": [
        194.4011993408203,
        22.162353515625,
        331.95269775390625,
        475.0075988769531
      ],
      "box_confidence": 0.8694103956222534,
      "class_id": 0,
      "class_name": "person",
      "keypoints": {
        "nose": {
          "x": 262.6680603027344,
          "y": 59.63777160644531,
          "confidence": 0.1565089225769043
        },
        "left_eye": {
          "x": 263.5986022949219,
          "y": 52.59657287597656,
          "confidence": 0.06419060379266739
        },
        "right_eye": {
          "x": 266.1996765136719,
          "y": 51.737396240234375,
          "confidence": 0.05699366703629494
        },
        "left_ear": {
          "x": 254.15118408203125,
          "y": 57.449981689453125,
          "confidence": 0.7135512232780457
        },
        "right_ear": {
          "x": 285.259765625,
          "y": 55.65614318847656,
          "confidence": 0.5986904501914978
        },
        "left_shoulder": {
          "x": 238.78123474121094,
          "y": 104.0980224609375,
          "confidence": 0.9732900857925415
        },
        "right_shoulder": {
          "x": 305.6844482421875,
          "y": 101.02159118652344,
          "confidence": 0.9785915613174438
        },
        "left_elbow": {
          "x": 230.20925903320312,
          "y": 171.08370971679688,
          "confidence": 0.8702171444892883
        },
        "right_elbow": {
          "x": 313.5125732421875,
          "y": 174.85214233398438,
          "confidence": 0.9070326685905457
        },
        "left_wrist": {
          "x": 241.0904083251953,
          "y": 195.5552520751953,
          "confidence": 0.7166547775268555
        },
        "right_wrist": {
          "x": 315.2947692871094,
          "y": 220.1720733642578,
          "confidence": 0.7670490741729736
        },
        "left_hip": {
          "x": 246.03257751464844,
          "y": 224.0162353515625,
          "confidence": 0.9971041083335876
        },
        "right_hip": {
          "x": 291.605224609375,
          "y": 222.0237579345703,
          "confidence": 0.9975234866142273
        },
        "left_knee": {
          "x": 239.41006469726562,
          "y": 339.0738525390625,
          "confidence": 0.9961048364639282
        },
        "right_knee": {
          "x": 290.5091247558594,
          "y": 339.8184814453125,
          "confidence": 0.9969646334648132
        },
        "left_ankle": {
          "x": 231.916748046875,
          "y": 446.9667053222656,
          "confidence": 0.9694474935531616
        },
        "right_ankle": {
          "x": 279.3667907714844,
          "y": 452.12835693359375,
          "confidence": 0.9744659066200256
        }
      }
    },
    {
      "bbox_xyxy": [
        113.5130615234375,
        75.59661865234375,
        225.5257568359375,
        284.14013671875
      ],
      "box_confidence": 0.43880248069763184,
      "class_id": 0,
      "class_name": "person",
      "keypoints": {
        "nose": {
          "x": 167.11068725585938,
          "y": 100.10135650634766,
          "confidence": 0.9812145233154297
        },
        "left_eye": {
          "x": 170.48703002929688,
          "y": 94.0063705444336,
          "confidence": 0.9250826835632324
        },
        "right_eye": {
          "x": 156.9968719482422,
          "y": 97.01151275634766,
          "confidence": 0.9683476686477661
        },
        "left_ear": {
          "x": 177.33853149414062,
          "y": 101.83417510986328,
          "confidence": 0.6273114085197449
        },
        "right_ear": {
          "x": 144.99363708496094,
          "y": 110.37669372558594,
          "confidence": 0.8678792119026184
        },
        "left_shoulder": {
          "x": 201.67984008789062,
          "y": 140.92051696777344,
          "confidence": 0.9805380702018738
        },
        "right_shoulder": {
          "x": 140.389404296875,
          "y": 145.61961364746094,
          "confidence": 0.9927411079406738
        },
        "left_elbow": {
          "x": 222.4962921142578,
          "y": 174.8257598876953,
          "confidence": 0.8705106377601624
        },
        "right_elbow": {
          "x": 152.2066650390625,
          "y": 191.6411590576172,
          "confidence": 0.966776430606842
        },
        "left_wrist": {
          "x": 217.9021759033203,
          "y": 149.82342529296875,
          "confidence": 0.850902795791626
        },
        "right_wrist": {
          "x": 179.04554748535156,
          "y": 226.19464111328125,
          "confidence": 0.932210385799408
        },
        "left_hip": {
          "x": 190.09661865234375,
          "y": 214.96359252929688,
          "confidence": 0.9613518118858337
        },
        "right_hip": {
          "x": 147.6466522216797,
          "y": 213.12887573242188,
          "confidence": 0.9755207300186157
        },
        "left_knee": {
          "x": 181.20864868164062,
          "y": 244.71127319335938,
          "confidence": 0.8711515069007874
        },
        "right_knee": {
          "x": 127.3609619140625,
          "y": 230.28298950195312,
          "confidence": 0.9163168668746948
        },
        "left_ankle": {
          "x": 190.17120361328125,
          "y": 308.1303405761719,
          "confidence": 0.6217519044876099
        },
        "right_ankle": {
          "x": 129.53463745117188,
          "y": 284.49493408203125,
          "confidence": 0.701018750667572
        }
      }
    }
  ]
}