{
  "image_path": "C:\\Projects\\PoseEstimation\\pose_images_backup\\e9ff15a_current\\img_116.jpg",
  "image_name": "img_116.jpg",
  "detections": [
    {
      "bbox_xyxy": [
        200.6326904296875,
        149.43182373046875,
        330.99273681640625,
        383.81695556640625
      ],
      "box_confidence": 0.9170830249786377,
      "class_id": 0,
      "class_name": "person",
      "keypoints": {
        "nose": {
          "x": 255.43344116210938,
          "y": 186.50929260253906,
          "confidence": 0.2717611789703369
        },
        "left_eye": {
          "x": 257.6749572753906,
          "y": 180.7908935546875,
          "confidence": 0.32277771830558777
        },
        "right_eye": {
          "x": 262.1903991699219,
          "y": 179.83973693847656,
          "confidence": 0.033618710935115814
        },
        "left_ear": {
          "x": 266.31011962890625,
          "y": 182.026611328125,
          "confidence": 0.9263644218444824
        },
        "right_ear": {
          "x": 289.8607177734375,
          "y": 179.89385986328125,
          "confidence": 0.14117231965065002
        },
        "left_shoulder": {
          "x": 257.5449523925781,
          "y": 209.48219299316406,
          "confidence": 0.988318920135498
        },
        "right_shoulder": {
          "x": 313.43365478515625,
          "y": 208.6705780029297,
          "confidence": 0.889094352722168
        },
        "left_elbow": {
          "x": 218.7639923095703,
          "y": 231.97821044921875,
          "confidence": 0.9650964736938477
        },
        "right_elbow": {
          "x": 309.998779296875,
          "y": 244.5774688720703,
          "confidence": 0.5227380990982056
        },
        "left_wrist": {
          "x": 236.36102294921875,
          "y": 200.94998168945312,
          "confidence": 0.8899389505386353
        },
        "right_wrist": {
          "x": 287.1907958984375,
          "y": 230.8915557861328,
          "confidence": 0.431240439414978
        },
        "left_hip": {
          "x": 280.39141845703125,
          "y": 305.753173828125,
          "confidence": 0.9885596632957458
        },
        "right_hip": {
          "x": 315.2223205566406,
          "y": 303.5586853027344,
          "confidence": 0.9664738178253174
        },
        "left_knee": {
          "x": 281.0313720703125,
          "y": 388.6275634765625,
          "confidence": 0.9383461475372314
        },
        "right_knee": {
          "x": 301.5646667480469,
          "y": 377.8099670410156,
          "confidence": 0.8411875367164612
        },
        "left_ankle": {
          "x": 291.4523620605469,
          "y": 443.06829833984375,
          "confidence": 0.6199549436569214
        },
        "right_ankle": {
          "x": 300.00054931640625,
          "y": 427.6900329589844,
          "confidence": 0.46954455971717834
        }
      }
    },
    {
      "bbox_xyxy": [
        409.55389404296875,
        140.6375732421875,
        483.02777099609375,
        317.146728515625
      ],
      "box_confidence": 0.8091491460800171,
      "class_id": 0,
      "class_name": "person",
      "keypoints": {
        "nose": {
          "x": 429.6430358886719,
          "y": 165.8570098876953,
          "confidence": 0.7486283183097839
        },
        "left_eye": {
          "x": 432.3985595703125,
          "y": 161.4873504638672,
          "confidence": 0.8246995806694031
        },
        "right_eye": {
          "x": 431.78125,
          "y": 160.5708465576172,
          "confidence": 0.1713496893644333
        },
        "left_ear": {
          "x": 446.4492492675781,
          "y": 165.62806701660156,
          "confidence": 0.9174293875694275
        },
        "right_ear": {
          "x": 447.4991760253906,
          "y": 162.43209838867188,
          "confidence": 0.09036193788051605
        },
        "left_shoulder": {
          "x": 459.3883361816406,
          "y": 196.50106811523438,
          "confidence": 0.9928955435752869
        },
        "right_shoulder": {
          "x": 454.1601257324219,
          "y": 191.91033935546875,
          "confidence": 0.8427180051803589
        },
        "left_elbow": {
          "x": 464.4902038574219,
          "y": 241.1864471435547,
          "confidence": 0.988699734210968
        },
        "right_elbow": {
          "x": 453.9876403808594,
          "y": 234.0019989013672,
          "confidence": 0.481668084859848
        },
        "left_wrist": {
          "x": 430.93536376953125,
          "y": 247.9369659423828,
          "confidence": 0.9690379500389099
        },
        "right_wrist": {
          "x": 431.0727844238281,
          "y": 238.4407958984375,
          "confidence": 0.5361078977584839
        },
        "left_hip": {
          "x": 458.19708251953125,
          "y": 277.0734558105469,
          "confidence": 0.9729169011116028
        },
        "right_hip": {
          "x": 454.9886169433594,
          "y": 273.5968017578125,
          "confidence": 0.8757442831993103
        },
        "left_knee": {
          "x": 458.9700927734375,
          "y": 334.8533630371094,
          "confidence": 0.8094949126243591
        },
        "right_knee": {
          "x": 454.5938415527344,
          "y": 331.1418762207031,
          "confidence": 0.4742916226387024
        },
        "left_ankle": {
          "x": 462.5706481933594,
          "y": 381.9714050292969,
          "confidence": 0.2807295322418213
        },
        "right_ankle": {
          "x": 455.9601745605469,
          "y": 376.22222900390625,
          "confidence": 0.1309785097837448
        }
      }
    },
    {
      "bbox_xyxy": [
        126.96074676513672,
        0.018280029296875,
        175.78179931640625,
        172.66221618652344
      ],
      "box_confidence": 0.7022566199302673,
      "class_id": 0,
      "class_name": "person",
      "keypoints": {
        "nose": {
          "x": 134.0642852783203,
          "y": 7.105842590332031,
          "confidence": 0.39618316292762756
        },
        "left_eye": {
          "x": 135.45506286621094,
          "y": 3.2022323608398438,
          "confidence": 0.4179731011390686
        },
        "right_eye": {
          "x": 134.24386596679688,
          "y": 3.411151885986328,
          "confidence": 0.11919201165437698
        },
        "left_ear": {
          "x": 141.057373046875,
          "y": 4.4121551513671875,
          "confidence": 0.6561499238014221
        },
        "right_ear": {
          "x": 142.9295196533203,
          "y": 3.8522720336914062,
          "confidence": 0.1296887844800949
        },
        "left_shoulder": {
          "x": 149.37623596191406,
          "y": 26.8343505859375,
          "confidence": 0.9553700089454651
        },
        "right_shoulder": {
          "x": 148.00119018554688,
          "y": 26.1064453125,
          "confidence": 0.7506988644599915
        },
        "left_elbow": {
          "x": 158.84597778320312,
          "y": 63.95466232299805,
          "confidence": 0.9186012744903564
        },
        "right_elbow": {
          "x": 159.39889526367188,
          "y": 63.856590270996094,
          "confidence": 0.4347285032272339
        },
        "left_wrist": {
          "x": 153.4251251220703,
          "y": 62.416324615478516,
          "confidence": 0.818780779838562
        },
        "right_wrist": {
          "x": 156.8639678955078,
          "y": 62.615352630615234,
          "confidence": 0.3943271338939667
        },
        "left_hip": {
          "x": 152.5984649658203,
          "y": 93.21318054199219,
          "confidence": 0.9684577584266663
        },
        "right_hip": {
          "x": 152.20249938964844,
          "y": 93.36591339111328,
          "confidence": 0.9182312488555908
        },
        "left_knee": {
          "x": 152.1033477783203,
          "y": 138.1141357421875,
          "confidence": 0.938488781452179
        },
        "right_knee": {
          "x": 155.27008056640625,
          "y": 139.13796997070312,
          "confidence": 0.8598548173904419
        },
        "left_ankle": {
          "x": 161.353271484375,
          "y": 172.62176513671875,
          "confidence": 0.8280166983604431
        },
        "right_ankle": {
          "x": 165.10182189941406,
          "y": 172.81588745117188,
          "confidence": 0.7327374219894409
        }
      }
    },
    {
      "bbox_xyxy": [
        59.28129577636719,
        12.091873168945312,
        115.38304138183594,
        156.9119415283203
      ],
      "box_confidence": 0.6147395372390747,
      "class_id": 0,
      "class_name": "person",
      "keypoints": {
        "nose": {
          "x": 74.13672637939453,
          "y": 24.560791015625,
          "confidence": 0.32964521646499634
        },
        "left_eye": {
          "x": 75.2421875,
          "y": 21.83905029296875,
          "confidence": 0.3128700256347656
        },
        "right_eye": {
          "x": 74.49190521240234,
          "y": 21.825927734375,
          "confidence": 0.11559420078992844
        },
        "left_ear": {
          "x": 78.61093139648438,
          "y": 23.10912322998047,
          "confidence": 0.5946345925331116
        },
        "right_ear": {
          "x": 81.81746673583984,
          "y": 22.84252166748047,
          "confidence": 0.1694299578666687
        },
        "left_shoulder": {
          "x": 82.0338134765625,
          "y": 38.85475158691406,
          "confidence": 0.9286128878593445
        },
        "right_shoulder": {
          "x": 85.2376480102539,
          "y": 37.655181884765625,
          "confidence": 0.8640971779823303
        },
        "left_elbow": {
          "x": 79.83418273925781,
          "y": 60.88792419433594,
          "confidence": 0.8356800079345703
        },
        "right_elbow": {
          "x": 79.24533081054688,
          "y": 58.10686111450195,
          "confidence": 0.5639168620109558
        },
        "left_wrist": {
          "x": 72.73542022705078,
          "y": 70.49653625488281,
          "confidence": 0.702363133430481
        },
        "right_wrist": {
          "x": 71.80091857910156,
          "y": 67.92304229736328,
          "confidence": 0.4654996991157532
        },
        "left_hip": {
          "x": 86.32121276855469,
          "y": 83.0398941040039,
          "confidence": 0.9664915204048157
        },
        "right_hip": {
          "x": 89.88906860351562,
          "y": 82.3777847290039,
          "confidence": 0.9522421956062317
        },
        "left_knee": {
          "x": 82.91399383544922,
          "y": 116.7012939453125,
          "confidence": 0.9538125991821289
        },
        "right_knee": {
          "x": 93.86744689941406,
          "y": 116.1280746459961,
          "confidence": 0.927101194858551
        },
        "left_ankle": {
          "x": 83.53108215332031,
          "y": 146.02481079101562,
          "confidence": 0.9090273380279541
        },
        "right_ankle": {
          "x": 99.25221252441406,
          "y": 144.31927490234375,
          "confidence": 0.8759523630142212
        }
      }
    }
  ]
}