{
  "image_path": "C:\\Projects\\PoseEstimation\\pose_images_backup\\jetson_images_final\\img_202.jpg",
  "image_name": "img_202.jpg",
  "detections": [
    {
      "bbox_xyxy": [
        185.2336883544922,
        82.06488037109375,
        389.16400146484375,
        346.82891845703125
      ],
      "box_confidence": 0.9140661358833313,
      "class_id": 0,
      "class_name": "person",
      "keypoints": {
        "nose": {
          "x": 226.93418884277344,
          "y": 142.50999450683594,
          "confidence": 0.8153963088989258
        },
        "left_eye": {
          "x": 227.61221313476562,
          "y": 137.82489013671875,
          "confidence": 0.7948713302612305
        },
        "right_eye": {
          "x": 223.7252960205078,
          "y": 135.75851440429688,
          "confidence": 0.2677602469921112
        },
        "left_ear": {
          "x": 239.2528533935547,
          "y": 121.29344177246094,
          "confidence": 0.743992805480957
        },
        "right_ear": {
          "x": 221.7565155029297,
          "y": 117.82149505615234,
          "confidence": 0.06738056987524033
        },
        "left_shoulder": {
          "x": 271.43780517578125,
          "y": 120.4268569946289,
          "confidence": 0.9937928915023804
        },
        "right_shoulder": {
          "x": 238.9252471923828,
          "y": 115.65836334228516,
          "confidence": 0.9386952519416809
        },
        "left_elbow": {
          "x": 272.4862060546875,
          "y": 182.29312133789062,
          "confidence": 0.9953303337097168
        },
        "right_elbow": {
          "x": 242.8642578125,
          "y": 178.42364501953125,
          "confidence": 0.9016658067703247
        },
        "left_wrist": {
          "x": 254.07968139648438,
          "y": 247.54080200195312,
          "confidence": 0.9882963299751282
        },
        "right_wrist": {
          "x": 226.632568359375,
          "y": 226.89547729492188,
          "confidence": 0.9033827185630798
        },
        "left_hip": {
          "x": 339.2116394042969,
          "y": 152.97708129882812,
          "confidence": 0.9985466599464417
        },
        "right_hip": {
          "x": 308.7735595703125,
          "y": 146.68597412109375,
          "confidence": 0.9959123730659485
        },
        "left_knee": {
          "x": 326.0694274902344,
          "y": 233.05213928222656,
          "confidence": 0.9976994395256042
        },
        "right_knee": {
          "x": 255.12213134765625,
          "y": 196.1675567626953,
          "confidence": 0.992671012878418
        },
        "left_ankle": {
          "x": 360.308349609375,
          "y": 322.6053161621094,
          "confidence": 0.9882742166519165
        },
        "right_ankle": {
          "x": 269.1061706542969,
          "y": 257.3310241699219,
          "confidence": 0.9798300266265869
        }
      }
    },
    {
      "bbox_xyxy": [
        326.290283203125,
        188.5355682373047,
        638.3336181640625,
        479.16717529296875
      ],
      "box_confidence": 0.8481170535087585,
      "class_id": 0,
      "class_name": "person",
      "keypoints": {
        "nose": {
          "x": 525.7172241210938,
          "y": 222.09410095214844,
          "confidence": 0.8641906380653381
        },
        "left_eye": {
          "x": 531.5470581054688,
          "y": 218.279052734375,
          "confidence": 0.8760659098625183
        },
        "right_eye": {
          "x": 529.3958740234375,
          "y": 215.6414337158203,
          "confidence": 0.30826863646507263
        },
        "left_ear": {
          "x": 555.1658935546875,
          "y": 224.59423828125,
          "confidence": 0.8831697106361389
        },
        "right_ear": {
          "x": 544.573486328125,
          "y": 218.0974884033203,
          "confidence": 0.05661795660853386
        },
        "left_shoulder": {
          "x": 590.43798828125,
          "y": 261.6195068359375,
          "confidence": 0.9886568188667297
        },
        "right_shoulder": {
          "x": 537.8787841796875,
          "y": 242.52618408203125,
          "confidence": 0.9257206320762634
        },
        "left_elbow": {
          "x": 621.667236328125,
          "y": 293.2771911621094,
          "confidence": 0.9791572690010071
        },
        "right_elbow": {
          "x": 500.0486145019531,
          "y": 252.93714904785156,
          "confidence": 0.7929111123085022
        },
        "left_wrist": {
          "x": 595.4946899414062,
          "y": 317.9291687011719,
          "confidence": 0.9707911014556885
        },
        "right_wrist": {
          "x": 492.6415100097656,
          "y": 272.87396240234375,
          "confidence": 0.7842231392860413
        },
        "left_hip": {
          "x": 534.0897216796875,
          "y": 350.9200134277344,
          "confidence": 0.9910373687744141
        },
        "right_hip": {
          "x": 504.51153564453125,
          "y": 329.8630065917969,
          "confidence": 0.9769504070281982
        },
        "left_knee": {
          "x": 453.1069030761719,
          "y": 378.97039794921875,
          "confidence": 0.9798628687858582
        },
        "right_knee": {
          "x": 429.5451965332031,
          "y": 351.17584228515625,
          "confidence": 0.9525970816612244
        },
        "left_ankle": {
          "x": 387.6436767578125,
          "y": 470.6490173339844,
          "confidence": 0.8798282146453857
        },
        "right_ankle": {
          "x": 386.93621826171875,
          "y": 438.1421813964844,
          "confidence": 0.81391841173172
        }
      }
    }
  ]
}