{
  "image_path": "C:\\Projects\\PoseEstimation\\pose_images_backup\\jetson_images_final\\img_189.jpg",
  "image_name": "img_189.jpg",
  "detections": [
    {
      "bbox_xyxy": [
        178.133056640625,
        175.74395751953125,
        412.334716796875,
        480.0
      ],
      "box_confidence": 0.8774147629737854,
      "class_id": 0,
      "class_name": "person",
      "keypoints": {
        "nose": {
          "x": 343.4048767089844,
          "y": 221.29495239257812,
          "confidence": 0.9777413010597229
        },
        "left_eye": {
          "x": 351.1592102050781,
          "y": 214.890625,
          "confidence": 0.9749666452407837
        },
        "right_eye": {
          "x": 343.4882507324219,
          "y": 212.46109008789062,
          "confidence": 0.7449125051498413
        },
        "left_ear": {
          "x": 376.9938049316406,
          "y": 216.43365478515625,
          "confidence": 0.9479911923408508
        },
        "right_ear": {
          "x": 353.55242919921875,
          "y": 212.42184448242188,
          "confidence": 0.14678697288036346
        },
        "left_shoulder": {
          "x": 397.9991455078125,
          "y": 258.68890380859375,
          "confidence": 0.9967030882835388
        },
        "right_shoulder": {
          "x": 355.5860290527344,
          "y": 244.15933227539062,
          "confidence": 0.9805203080177307
        },
        "left_elbow": {
          "x": 385.0477294921875,
          "y": 327.3699035644531,
          "confidence": 0.9907878041267395
        },
        "right_elbow": {
          "x": 332.163818359375,
          "y": 300.87139892578125,
          "confidence": 0.9113656878471375
        },
        "left_wrist": {
          "x": 331.40985107421875,
          "y": 308.6520690917969,
          "confidence": 0.9864952564239502
        },
        "right_wrist": {
          "x": 309.34381103515625,
          "y": 288.968505859375,
          "confidence": 0.9033550024032593
        },
        "left_hip": {
          "x": 349.4345397949219,
          "y": 350.279296875,
          "confidence": 0.9936938881874084
        },
        "right_hip": {
          "x": 322.01446533203125,
          "y": 331.0798034667969,
          "confidence": 0.9855443835258484
        },
        "left_knee": {
          "x": 288.42193603515625,
          "y": 357.8282165527344,
          "confidence": 0.9889876246452332
        },
        "right_knee": {
          "x": 257.31072998046875,
          "y": 324.1290588378906,
          "confidence": 0.9738577604293823
        },
        "left_ankle": {
          "x": 238.236572265625,
          "y": 465.619140625,
          "confidence": 0.9354630708694458
        },
        "right_ankle": {
          "x": 224.8311767578125,
          "y": 425.4886474609375,
          "confidence": 0.8977571725845337
        }
      }
    }
  ]
}