{
  "image_path": "C:\\Projects\\PoseEstimation\\pose_images_backup\\jetson_images_final\\img_31.jpg",
  "image_name": "img_31.jpg",
  "detections": [
    {
      "bbox_xyxy": [
        348.7069091796875,
        115.6705322265625,
        538.5189208984375,
        480.0
      ],
      "box_confidence": 0.910510778427124,
      "class_id": 0,
      "class_name": "person",
      "keypoints": {
        "nose": {
          "x": 416.733154296875,
          "y": 159.72071838378906,
          "confidence": 0.9902132153511047
        },
        "left_eye": {
          "x": 426.2744140625,
          "y": 152.89901733398438,
          "confidence": 0.9694892764091492
        },
        "right_eye": {
          "x": 408.927734375,
          "y": 150.73941040039062,
          "confidence": 0.9673187136650085
        },
        "left_ear": {
          "x": 439.9503173828125,
          "y": 160.72689819335938,
          "confidence": 0.7936319708824158
        },
        "right_ear": {
          "x": 397.0740051269531,
          "y": 156.39639282226562,
          "confidence": 0.7781469821929932
        },
        "left_shoulder": {
          "x": 450.3228759765625,
          "y": 204.59127807617188,
          "confidence": 0.9952657222747803
        },
        "right_shoulder": {
          "x": 376.1955261230469,
          "y": 206.9517059326172,
          "confidence": 0.9942471981048584
        },
        "left_elbow": {
          "x": 465.7842712402344,
          "y": 260.06195068359375,
          "confidence": 0.9830448627471924
        },
        "right_elbow": {
          "x": 360.2630310058594,
          "y": 275.5660400390625,
          "confidence": 0.978029727935791
        },
        "left_wrist": {
          "x": 466.7869567871094,
          "y": 297.2217102050781,
          "confidence": 0.9770433306694031
        },
        "right_wrist": {
          "x": 391.6104431152344,
          "y": 303.1358337402344,
          "confidence": 0.9753845930099487
        },
        "left_hip": {
          "x": 446.1610107421875,
          "y": 306.9729919433594,
          "confidence": 0.9962067604064941
        },
        "right_hip": {
          "x": 394.79827880859375,
          "y": 311.4565734863281,
          "confidence": 0.9956663846969604
        },
        "left_knee": {
          "x": 496.385498046875,
          "y": 351.2876892089844,
          "confidence": 0.9884501695632935
        },
        "right_knee": {
          "x": 417.27618408203125,
          "y": 356.1671142578125,
          "confidence": 0.988509476184845
        },
        "left_ankle": {
          "x": 485.56085205078125,
          "y": 451.6785583496094,
          "confidence": 0.9166819453239441
        },
        "right_ankle": {
          "x": 410.6036376953125,
          "y": 458.0057678222656,
          "confidence": 0.9188721179962158
        }
      }
    },
    {
      "bbox_xyxy": [
        59.03076171875,
        37.42645263671875,
        207.73660278320312,
        477.79547119140625
      ],
      "box_confidence": 0.8975375890731812,
      "class_id": 0,
      "class_name": "person",
      "keypoints": {
        "nose": {
          "x": 146.68386840820312,
          "y": 81.0091552734375,
          "confidence": 0.9924579858779907
        },
        "left_eye": {
          "x": 157.53085327148438,
          "y": 73.00407409667969,
          "confidence": 0.9737514853477478
        },
        "right_eye": {
          "x": 137.54783630371094,
          "y": 71.20591735839844,
          "confidence": 0.976055920124054
        },
        "left_ear": {
          "x": 170.960205078125,
          "y": 82.544677734375,
          "confidence": 0.7864911556243896
        },
        "right_ear": {
          "x": 122.27272033691406,
          "y": 77.77972412109375,
          "confidence": 0.8073664307594299
        },
        "left_shoulder": {
          "x": 184.67889404296875,
          "y": 142.95101928710938,
          "confidence": 0.9942418336868286
        },
        "right_shoulder": {
          "x": 95.57591247558594,
          "y": 138.39874267578125,
          "confidence": 0.994005560874939
        },
        "left_elbow": {
          "x": 194.43890380859375,
          "y": 224.07928466796875,
          "confidence": 0.9739440083503723
        },
        "right_elbow": {
          "x": 70.4599838256836,
          "y": 217.5507049560547,
          "confidence": 0.9716021418571472
        },
        "left_wrist": {
          "x": 195.97421264648438,
          "y": 299.44891357421875,
          "confidence": 0.9499341249465942
        },
        "right_wrist": {
          "x": 81.94253540039062,
          "y": 290.93505859375,
          "confidence": 0.9507079720497131
        },
        "left_hip": {
          "x": 166.3408966064453,
          "y": 287.7064208984375,
          "confidence": 0.993556559085846
        },
        "right_hip": {
          "x": 107.09994506835938,
          "y": 286.8901672363281,
          "confidence": 0.9936034083366394
        },
        "left_knee": {
          "x": 169.3055877685547,
          "y": 405.05047607421875,
          "confidence": 0.887888491153717
        },
        "right_knee": {
          "x": 93.88145446777344,
          "y": 403.25262451171875,
          "confidence": 0.8872888684272766
        },
        "left_ankle": {
          "x": 164.1795654296875,
          "y": 480.0,
          "confidence": 0.272601455450058
        },
        "right_ankle": {
          "x": 89.25508117675781,
          "y": 480.0,
          "confidence": 0.26775678992271423
        }
      }
    },
    {
      "bbox_xyxy": [
        179.22633361816406,
        211.39732360839844,
        408.1427001953125,
        480.0
      ],
      "box_confidence": 0.8168308734893799,
      "class_id": 0,
      "class_name": "person",
      "keypoints": {
        "nose": {
          "x": 308.7232360839844,
          "y": 270.5016784667969,
          "confidence": 0.9915598034858704
        },
        "left_eye": {
          "x": 322.505615234375,
          "y": 260.18853759765625,
          "confidence": 0.9777465462684631
        },
        "right_eye": {
          "x": 299.00946044921875,
          "y": 258.6602783203125,
          "confidence": 0.9749828577041626
        },
        "left_ear": {
          "x": 341.40966796875,
          "y": 269.5050354003906,
          "confidence": 0.8538526892662048
        },
        "right_ear": {
          "x": 285.83404541015625,
          "y": 266.12347412109375,
          "confidence": 0.7439261674880981
        },
        "left_shoulder": {
          "x": 364.40289306640625,
          "y": 337.6363830566406,
          "confidence": 0.9869599938392639
        },
        "right_shoulder": {
          "x": 263.3486633300781,
          "y": 333.359619140625,
          "confidence": 0.9892712831497192
        },
        "left_elbow": {
          "x": 382.15301513671875,
          "y": 423.67291259765625,
          "confidence": 0.8788062334060669
        },
        "right_elbow": {
          "x": 238.7955322265625,
          "y": 415.05950927734375,
          "confidence": 0.9027225375175476
        },
        "left_wrist": {
          "x": 387.75177001953125,
          "y": 478.5437316894531,
          "confidence": 0.6940864324569702
        },
        "right_wrist": {
          "x": 200.77931213378906,
          "y": 480.0,
          "confidence": 0.7054708003997803
        },
        "left_hip": {
          "x": 338.74658203125,
          "y": 474.47528076171875,
          "confidence": 0.6435490846633911
        },
        "right_hip": {
          "x": 272.91546630859375,
          "y": 469.2325744628906,
          "confidence": 0.6766276955604553
        },
        "left_knee": {
          "x": 332.6794128417969,
          "y": 480.0,
          "confidence": 0.04873256757855415
        },
        "right_knee": {
          "x": 243.65353393554688,
          "y": 473.65045166015625,
          "confidence": 0.049854520708322525
        },
        "left_ankle": {
          "x": 358.24127197265625,
          "y": 480.0,
          "confidence": 0.008473841473460197
        },
        "right_ankle": {
          "x": 285.9091796875,
          "y": 463.3429870605469,
          "confidence": 0.008763276040554047
        }
      }
    }
  ]
}